swarmopt/__init__.py
swarmopt/functions.py
swarmopt/swarm.py
swarmopt-0.2.0.dist-info/licenses/LICENSE.md
swarmopt-0.2.0.dist-info/METADATA
swarmopt-0.2.0.dist-info/WHEEL
swarmopt-0.2.0.dist-info/top_level.txt
swarmopt-0.2.0.dist-info/RECORD
