Metadata-Version: 2.4
Name: swarmopt
Version: 0.2.0
Summary: Advanced Particle Swarm Optimization with multiobjective support, respect boundaries, and cooperative swarms
Home-page: https://github.com/siokcronin/swarmopt
Author: Siobhan K Cronin
Author-email: siobhankcronin@gmail.com
License: MIT
Project-URL: Bug Reports, https://github.com/siokcronin/swarmopt/issues
Project-URL: Source, https://github.com/siokcronin/swarmopt
Project-URL: Documentation, https://github.com/siokcronin/swarmopt/tree/main/docs
Keywords: particle swarm optimization,PSO,swarm intelligence,optimization,multiobjective,hyperparameter tuning,cooperative PSO,NSGA-II,machine learning
Classifier: Development Status :: 4 - Beta
Classifier: Intended Audience :: Science/Research
Classifier: Intended Audience :: Developers
Classifier: License :: OSI Approved :: MIT License
Classifier: Programming Language :: Python :: 3
Classifier: Programming Language :: Python :: 3.7
Classifier: Programming Language :: Python :: 3.8
Classifier: Programming Language :: Python :: 3.9
Classifier: Programming Language :: Python :: 3.10
Classifier: Programming Language :: Python :: 3.11
Classifier: Topic :: Scientific/Engineering :: Artificial Intelligence
Classifier: Topic :: Scientific/Engineering :: Mathematics
Classifier: Topic :: Software Development :: Libraries :: Python Modules
Requires-Python: >=3.7
License-File: LICENSE.md
Requires-Dist: numpy>=1.19.0
Provides-Extra: viz
Requires-Dist: matplotlib>=3.3.0; extra == "viz"
Provides-Extra: multiobjective
Requires-Dist: scipy>=1.5.0; extra == "multiobjective"
Provides-Extra: tda
Requires-Dist: giotto-tda>=0.5.0; extra == "tda"
Provides-Extra: all
Requires-Dist: matplotlib>=3.3.0; extra == "all"
Requires-Dist: scipy>=1.5.0; extra == "all"
Dynamic: author
Dynamic: author-email
Dynamic: classifier
Dynamic: description
Dynamic: description-content-type
Dynamic: home-page
Dynamic: keywords
Dynamic: license
Dynamic: license-file
Dynamic: project-url
Dynamic: provides-extra
Dynamic: requires-dist
Dynamic: requires-python
Dynamic: summary
